bottle_argsmap.py
bottle_argsmap-0.1.1.dist-info/LICENSE
bottle_argsmap-0.1.1.dist-info/WHEEL
bottle_argsmap-0.1.1.dist-info/METADATA
bottle_argsmap-0.1.1.dist-info/RECORD
