Metadata-Version: 2.1
Name: bottle-argsmap
Version: 0.1.1
Summary: 
Home-page: https://github.com/Cologler/bottle_argsmap-python
License: MIT
Author: Cologler
Author-email: skyoflw@gmail.com
Requires-Python: >=3.8,<4.0
Classifier: License :: OSI Approved :: MIT License
Classifier: Programming Language :: Python :: 3
Classifier: Programming Language :: Python :: 3.8
Classifier: Programming Language :: Python :: 3.9
Requires-Dist: anyioc (>=0.11.1,<0.12.0)
Requires-Dist: bottle (>=0.12.19,<0.13.0)
